textual_worldmap/__init__.py
textual_worldmap/worldmapwidget.py
textual_worldmap-0.2.0.dist-info/LICENSE
textual_worldmap-0.2.0.dist-info/METADATA
textual_worldmap-0.2.0.dist-info/WHEEL
textual_worldmap-0.2.0.dist-info/RECORD
